flask_babel_js/__init__.py
flask_babel_js-1.0.3.dist-info/METADATA
flask_babel_js-1.0.3.dist-info/WHEEL
flask_babel_js-1.0.3.dist-info/licenses/LICENSE
flask_babel_js-1.0.3.dist-info/RECORD
