Metadata-Version: 2.4
Name: Flask-Babel-JS
Version: 1.0.3
Summary: Flask extension to add Flask-Babel translations in JS
License-File: LICENSE
Classifier: Environment :: Web Environment
Classifier: Intended Audience :: Developers
Classifier: License :: OSI Approved :: BSD License
Classifier: Operating System :: OS Independent
Classifier: Programming Language :: Python
Classifier: Topic :: Internet :: WWW/HTTP :: Dynamic Content
Classifier: Topic :: Software Development :: Libraries :: Python Modules
Requires-Python: >=3.9
Requires-Dist: flask-babel~=4.0
Requires-Dist: flask~=3.1
